eegio/__init__.py
eegio/base/__init__.py
eegio/base/config.py
eegio/base/dataset_test/__init__.py
eegio/base/dataset_test/dataset_tester.py
eegio/base/format/__init__.py
eegio/base/format/baseadapter.py
eegio/base/objects/__init__.py
eegio/base/objects/derivatives/__init__.py
eegio/base/objects/derivatives/basedataobject.py
eegio/base/objects/derivatives/result_object.py
eegio/base/objects/electrodes/__init__.py
eegio/base/objects/electrodes/elecs.py
eegio/base/objects/electrodes/electrode.py
eegio/base/utils/__init__.py
eegio/base/utils/bids_helper.py
eegio/base/utils/contacts_list_helper.py
eegio/base/utils/data_structures_utils.py
eegio/base/utils/normalizations.py
eegio/base/utils/scalp_eeg_helper.py
eegio/base/utils/scrubber.py
eegio/loaders/__init__.py
eegio/loaders/bids/__init__.py
eegio/loaders/bids/basebids.py
eegio/loaders/bids/bids_patient.py
eegio/loaders/bids/bids_run.py
eegio/loaders/bids/bidsio.py
eegio/loaders/derivatives/__init__.py
eegio/loaders/derivatives/baseloader.py
eegio/loaders/derivatives/result_loader.py
eegio/writers/__init__.py
eegio/writers/basewrite.py
eegio/writers/saveas.py
eegio-0.1.3.dist-info/LICENSE
eegio-0.1.3.dist-info/METADATA
eegio-0.1.3.dist-info/WHEEL
eegio-0.1.3.dist-info/top_level.txt
eegio-0.1.3.dist-info/RECORD
