Metadata-Version: 2.1
Name: eegio
Version: 0.1.3
Summary: EEGIO: An io package for eeg data that is MNE-Python and MNE-BIDS compatible .
Home-page: https://github.com/adam2392/eegio
Author: Adam Li
Author-email: adam2392@gmail.com
Maintainer: Adam Li
Maintainer-email: adam2392@gmail.com
License: GNU General Public License (GPL)
Download-URL: https://github.com/adam2392/eegio.git
Project-URL: Documentation, https://github.com/adam2392/eegio/docs/
Project-URL: Source, https://github.com/adam2392/eegio
Project-URL: Tracker, https://github.com/adam2392/eegio/issues
Keywords: EEG,epilepsy,research tools,IO tools
Platform: any
Classifier: Development Status :: 3 - Alpha
Classifier: Intended Audience :: Developers
Classifier: Intended Audience :: Science/Research
Classifier: Topic :: Scientific/Engineering :: Medical Science Apps.
Classifier: Topic :: Scientific/Engineering
Classifier: Topic :: Utilities
Classifier: License :: OSI Approved :: GNU General Public License (GPL)
Classifier: Programming Language :: Python :: 3.6
Classifier: Programming Language :: Python :: 3.7
Classifier: Programming Language :: Python :: Implementation
Classifier: Natural Language :: English
Requires-Dist: numpy (>=1.17.2)
Requires-Dist: scipy (>=1.3.1)
Requires-Dist: scikit-learn (>=0.21.3)
Requires-Dist: pandas (>=0.25.1)
Requires-Dist: mne (>=0.19)
Requires-Dist: mne-bids (>=0.3)
Requires-Dist: pybids (>=0.5.1)
Requires-Dist: pyEDFlib (==0.1.14)
Requires-Dist: xlrd (>=1.2.0)
